ceramic/__init__.py
ceramic/__version__.py
ceramic/client.py
ceramic/payloads.py
ceramic_py-0.1.0.dist-info/LICENSE
ceramic_py-0.1.0.dist-info/METADATA
ceramic_py-0.1.0.dist-info/WHEEL
ceramic_py-0.1.0.dist-info/top_level.txt
ceramic_py-0.1.0.dist-info/RECORD
