Metadata-Version: 2.1
Name: ceramic-py
Version: 0.1.0
Summary: Python client for ceramic streams.
Home-page: https://github.com/valory-xyz/ceramic-python-client.git
Author: Valory AG
License: Apache-2.0
Project-URL: Bug Reports, https://github.com/valory-xyz/ceramic-python-client/issues
Project-URL: Source, https://github.com/valory/ceramic-python-client
Classifier: Environment :: Console
Classifier: Environment :: Web Environment
Classifier: Development Status :: 2 - Pre-Alpha
Classifier: Intended Audience :: Developers
Classifier: License :: OSI Approved :: Apache Software License
Classifier: Natural Language :: English
Classifier: Operating System :: MacOS
Classifier: Operating System :: Microsoft
Classifier: Operating System :: Unix
Classifier: Programming Language :: Python :: 3.8
Classifier: Programming Language :: Python :: 3.9
Classifier: Programming Language :: Python :: 3.10
Classifier: Topic :: Communications
Classifier: Topic :: Internet
Classifier: Topic :: Scientific/Engineering
Classifier: Topic :: Software Development
Classifier: Topic :: System
Requires-Python: >=3.8
License-File: LICENSE
Requires-Dist: Authlib (==1.2.0)
Requires-Dist: dag-cbor (==0.2.2)
Requires-Dist: jsonpatch (==1.32)
Requires-Dist: multiformats (==0.1.4.post3)
Requires-Dist: requests (==2.28.2)
